dune/__init__.py
dune/fem/__init__.py
dune/fem/__main__.py
dune/fem/_adaptation.py
dune/fem/_fem.so
dune/fem/_spaceadaptation.py
dune/fem/plotting.py
dune/fem/view.py
dune/fem/discretefunction/__init__.py
dune/fem/discretefunction/_discretefunctions.py
dune/fem/discretefunction/_solvers.py
dune/fem/discretefunction/adaptive.py
dune/fem/discretefunction/eigen.py
dune/fem/discretefunction/istl.py
dune/fem/discretefunction/numpy.py
dune/fem/function/__init__.py
dune/fem/function/_functions.py
dune/fem/model/__init__.py
dune/fem/model/_models.py
dune/fem/operator/__init__.py
dune/fem/scheme/__init__.py
dune/fem/scheme/_schemes.py
dune/fem/scheme/dgmodel.py
dune/fem/space/__init__.py
dune/fem/space/_spaces.py
dune/fem/utility/__init__.py
dune/fenics/__init__.py
dune/fenics/_compatibility.py
dune/models/__init__.py
dune/models/localfunction.py
dune/models/elliptic/__init__.py
dune/models/elliptic/compiler.py
dune/models/elliptic/formfiles.py
dune/models/elliptic/model.py
dune/models/elliptic/ufl.py
dune/models/integrands/__init__.py
dune/models/integrands/compiler.py
dune/models/integrands/formfiles.py
dune/models/integrands/load.py
dune/models/integrands/model.py
dune/models/integrands/ufl.py
dune/source/__init__.py
dune/source/basemodel.py
dune/source/builtin.py
dune/source/common.py
dune/source/cplusplus.py
dune/source/expression.py
dune/source/fem.py
dune/source/function.py
dune/source/operator.py
dune/source/algorithm/__init__.py
dune/source/algorithm/extractincludes.py
dune/source/algorithm/extractvariables.py
dune/source/formatter/__init__.py
dune/source/formatter/expression.py
dune/ufl/__init__.py
dune/ufl/applyrestrictions.py
dune/ufl/codegen.py
dune/ufl/formfiles.py
dune/ufl/gatherderivatives.py
dune/ufl/latex.py
dune/ufl/linear.py
dune/ufl/tensors.py
dune_fem-2.8.0.dev20201214.data/data/include/dune/fem/version.hh
dune_fem-2.8.0.dev20201214.data/data/include/dune/fem/common/bindguard.hh
dune_fem-2.8.0.dev20201214.data/data/include/dune/fem/common/coordinate.hh
dune_fem-2.8.0.dev20201214.dist-info/AUTHORS
dune_fem-2.8.0.dev20201214.dist-info/COPYING
dune_fem-2.8.0.dev20201214.dist-info/LICENSE.md
dune_fem-2.8.0.dev20201214.dist-info/METADATA
dune_fem-2.8.0.dev20201214.dist-info/WHEEL
dune_fem-2.8.0.dev20201214.dist-info/top_level.txt
dune_fem-2.8.0.dev20201214.dist-info/RECORD
