Metadata-Version: 2.1
Name: dune-fem
Version: 2.8.0.dev20201214
Summary: A discretization module providing an implementation of mathematical abstractions to solve PDEs on parallel computers including local grid adaptivity, dynamic load balancing, and higher order discretization schemes
Home-page: https://gitlab.dune-project.org/dune-fem/dune-fem
Author: The Dune-Fem developer team
Author-email: dune-fem@lists.dune-project.org
License: UNKNOWN
Platform: UNKNOWN
Classifier: Programming Language :: C++
Classifier: Programming Language :: Python :: 3
Classifier: License :: OSI Approved :: GNU General Public License (GPL)
Requires-Python: >=3.4
Requires-Dist: UFL (==2017.1.0)
Requires-Dist: dune-alugrid (<=2.8.0.dev20201214)
Requires-Dist: dune-istl (<=2.8.0.dev20201214)
Requires-Dist: dune-localfunctions (<=2.8.0.dev20201214)
Requires-Dist: dune-grid (<=2.8.0.dev20201214)
